{
  "clients": [
    {
      "name": "Toranzo Fabricio",
      "email": "fa@mail.com",
      "id": "1"
    },
    {
      "id": "2",
      "name": "Iba침ez Benjamin",
      "email": "iba침@mail.com"
    },
    {
      "id": "3",
      "name": "Palacios Esteban",
      "email": "des@mail.com"
    },
    {
      "id": "4",
      "name": "Gonzalez Maria",
      "email": "maria@mail.com"
    },
    {
      "id": "c16e",
      "name": "Lola Mora",
      "email": "lolamora@gmail.com"
    }
  ],
  "services": [
    {
      "name": "Corte Cl치sico",
      "description": "Corte de pelo tradicional",
      "duration": 30,
      "price": 7000,
      "available": true,
      "id": "1"
    },
    {
      "name": "Tintura",
      "description": "Coloraci칩n completa del pelo",
      "duration": 150,
      "price": 20000,
      "available": true,
      "id": "2"
    },
    {
      "id": "813e",
      "name": "Corte Normal con lavado y secado",
      "description": "Corte normal puede incluir degrade o no con lavado y secado de pelo",
      "duration": 45,
      "price": 10000,
      "available": true
    }
  ],
  "appointments": [
    {
      "id": "1",
      "clientId": 1,
      "serviceId": 2,
      "date": "2025-10-22",
      "time": "10:00"
    },
    {
      "id": "2",
      "clientId": 2,
      "serviceId": 1,
      "date": "2025-10-22",
      "time": "12:00"
    },
    {
      "id": "5",
      "clientId": 1,
      "serviceId": 1,
      "date": "2025-10-23",
      "time": "11:00"
    },
    {
      "id": "8",
      "clientId": 3,
      "serviceId": 1,
      "date": "2025-11-12",
      "time": "12:15"
    },
    {
      "id": "9",
      "clientId": 4,
      "serviceId": 2,
      "date": "2025-11-12",
      "time": "15:00"
    },
    {
      "clientId": "c16e",
      "serviceId": "2",
      "date": "2025-11-14",
      "time": "21:20",
      "id": "1f41"
    }
  ]
}